pdm_scriptcomplete-0.0.2.dist-info/METADATA
pdm_scriptcomplete-0.0.2.dist-info/WHEEL
pdm_scriptcomplete-0.0.2.dist-info/entry_points.txt
pdm_scriptcomplete/__init__.py
pdm_scriptcomplete-0.0.2.dist-info/RECORD
