Metadata-Version: 2.1
Name: pdm-scriptcomplete
Version: 0.0.2
Summary: A PDM plugin that enables tab completion for pdm scripts
Keywords: pdm pdm-scriptcomplete
Author: Anton Bauer
License: MIT
Project-URL: Homepage, https://pypi.org/project/pdm-scriptcomplete/
Project-URL: Repository, https://github.com/g-wagen/pdm-scriptcomplete.git
Requires-Python: >=3.9
Requires-Dist: pdm>=2.5
